drawing/__init__.py
drawing/drawing.py
drawing/viewer.py
drawing_app-1.1.0.dist-info/METADATA
drawing_app-1.1.0.dist-info/WHEEL
drawing_app-1.1.0.dist-info/entry_points.txt
drawing_app-1.1.0.dist-info/top_level.txt
drawing_app-1.1.0.dist-info/RECORD
