Metadata-Version: 2.1
Name: drawing_app
Version: 1.1.0
Summary: A simple drawing application and image viewer.
Home-page: https://github.com/yourusername/drawing_app
Author: Your Name
Author-email: your.email@example.com
Classifier: Programming Language :: Python :: 3
Classifier: License :: OSI Approved :: MIT License
Classifier: Operating System :: OS Independent
Requires-Python: >=3.6
Requires-Dist: pygame
